mathext/BaseChange.py
mathext/Primes.py
mathext/__init__.py
mathools/__init__.py
mathools/base.py
mathools/primes.py
tests/__init__.py
tests/test_primes.py
mathools-0.1.1.dist-info/LICENSE
mathools-0.1.1.dist-info/METADATA
mathools-0.1.1.dist-info/WHEEL
mathools-0.1.1.dist-info/top_level.txt
mathools-0.1.1.dist-info/RECORD
