Metadata-Version: 2.1
Name: mathools
Version: 0.1.1
Summary: Some extra math tools
Home-page: https://github.com/JuliusRye/math-extended
Author: Julius Rye Bønnelykke
Author-email: juliusrye@gmail.com
License: MIT License
Platform: UNKNOWN
License-File: LICENSE
Requires-Dist: numpy (>=1.23.0)
